llama_index/llms/azure_openai/__init__.py
llama_index/llms/azure_openai/base.py
llama_index/llms/azure_openai/utils.py
basejump_llama_index_llms_azure_openai-0.3.2.post1.dist-info/METADATA
basejump_llama_index_llms_azure_openai-0.3.2.post1.dist-info/WHEEL
basejump_llama_index_llms_azure_openai-0.3.2.post1.dist-info/licenses/LICENSE
basejump_llama_index_llms_azure_openai-0.3.2.post1.dist-info/RECORD
