Metadata-Version: 2.4
Name: basejump-llama-index-llms-azure-openai
Version: 0.3.2.post1
Summary: llama-index llms azure openai integration
Author-email: Your Name <you@example.com>
License-Expression: MIT
License-File: LICENSE
Requires-Python: <4.0,>=3.9
Requires-Dist: azure-identity<2,>=1.15.0
Requires-Dist: basejump-llama-index-core<0.13,>=0.12.0
Requires-Dist: basejump-llama-index-llms-openai<0.4,>=0.3.0
Requires-Dist: httpx==0.25.2
